jupyterlab_open_url_parameter/__init__.py
jupyterlab_open_url_parameter/_version.py
jupyterlab_open_url_parameter-0.3.0.data/data/share/jupyter/labextensions/jupyterlab-open-url-parameter/package.json
jupyterlab_open_url_parameter-0.3.0.data/data/share/jupyter/labextensions/jupyterlab-open-url-parameter/static/568.01d8de54f0240b4168bd.js
jupyterlab_open_url_parameter-0.3.0.data/data/share/jupyter/labextensions/jupyterlab-open-url-parameter/static/747.81bc8c282a9a99aa0a8f.js
jupyterlab_open_url_parameter-0.3.0.data/data/share/jupyter/labextensions/jupyterlab-open-url-parameter/static/remoteEntry.c7a31b7a4c60a21a3aa0.js
jupyterlab_open_url_parameter-0.3.0.data/data/share/jupyter/labextensions/jupyterlab-open-url-parameter/static/style.js
jupyterlab_open_url_parameter-0.3.0.data/data/share/jupyter/labextensions/jupyterlab-open-url-parameter/static/third-party-licenses.json
jupyterlab_open_url_parameter-0.3.0.data/data/share/jupyter/labextensions/jupyterlab-open-url-parameter/install.json
jupyterlab_open_url_parameter-0.3.0.dist-info/METADATA
jupyterlab_open_url_parameter-0.3.0.dist-info/WHEEL
jupyterlab_open_url_parameter-0.3.0.dist-info/licenses/LICENSE
jupyterlab_open_url_parameter-0.3.0.dist-info/RECORD
