Metadata-Version: 2.1
Name: jupyterlab_open_url_parameter
Version: 0.3.0
Summary: JupyterLab extension to open files passed via a URL parameter
Project-URL: Homepage, https://github.com/jupyterlab-contrib/jupyterlab-open-url-parameter
Project-URL: Bug Tracker, https://github.com/jupyterlab-contrib/jupyterlab-open-url-parameter/issues
Project-URL: Repository, https://github.com/jupyterlab-contrib/jupyterlab-open-url-parameter.git
Author: JupyterLab Contrib Team
License: BSD 3-Clause License
License-File: LICENSE
Classifier: Framework :: Jupyter
Classifier: Framework :: Jupyter :: JupyterLab
Classifier: Framework :: Jupyter :: JupyterLab :: 4
Classifier: Framework :: Jupyter :: JupyterLab :: Extensions
Classifier: Framework :: Jupyter :: JupyterLab :: Extensions :: Prebuilt
Classifier: License :: OSI Approved :: BSD License
Classifier: Programming Language :: Python
Classifier: Programming Language :: Python :: 3
Classifier: Programming Language :: Python :: 3.8
Classifier: Programming Language :: Python :: 3.9
Classifier: Programming Language :: Python :: 3.10
Classifier: Programming Language :: Python :: 3.11
Classifier: Programming Language :: Python :: 3.12
Requires-Python: >=3.8
